{
    "depot": {
        "x": 173,
        "y": 882,
        "node_type": "depot",
        "id": 0
    },
    "final_destination": {
        "x": 978,
        "y": 895,
        "node_type": "final",
        "id": 16
    },
    "pickup_nodes": [
        {
            "x": 554,
            "y": 46,
            "node_type": "pickup",
            "id": 1
        },
        {
            "x": 162,
            "y": 830,
            "node_type": "pickup",
            "id": 2
        },
        {
            "x": 899,
            "y": 833,
            "node_type": "pickup",
            "id": 3
        },
        {
            "x": 151,
            "y": 519,
            "node_type": "pickup",
            "id": 4
        },
        {
            "x": 406,
            "y": 633,
            "node_type": "pickup",
            "id": 5
        },
        {
            "x": 947,
            "y": 849,
            "node_type": "pickup",
            "id": 6
        },
        {
            "x": 57,
            "y": 979,
            "node_type": "pickup",
            "id": 7
        },
        {
            "x": 848,
            "y": 965,
            "node_type": "pickup",
            "id": 8
        },
        {
            "x": 25,
            "y": 197,
            "node_type": "pickup",
            "id": 9
        },
        {
            "x": 895,
            "y": 170,
            "node_type": "pickup",
            "id": 10
        },
        {
            "x": 190,
            "y": 815,
            "node_type": "pickup",
            "id": 11
        },
        {
            "x": 679,
            "y": 263,
            "node_type": "pickup",
            "id": 12
        },
        {
            "x": 682,
            "y": 932,
            "node_type": "pickup",
            "id": 13
        },
        {
            "x": 910,
            "y": 140,
            "node_type": "pickup",
            "id": 14
        },
        {
            "x": 712,
            "y": 541,
            "node_type": "pickup",
            "id": 15
        }
    ],
    "delivery_nodes": [
        {
            "x": 916,
            "y": 254,
            "node_type": "delivery",
            "id": 1
        },
        {
            "x": 70,
            "y": 812,
            "node_type": "delivery",
            "id": 2
        },
        {
            "x": 930,
            "y": 18,
            "node_type": "delivery",
            "id": 3
        },
        {
            "x": 131,
            "y": 875,
            "node_type": "delivery",
            "id": 4
        },
        {
            "x": 650,
            "y": 523,
            "node_type": "delivery",
            "id": 5
        },
        {
            "x": 875,
            "y": 987,
            "node_type": "delivery",
            "id": 6
        },
        {
            "x": 163,
            "y": 16,
            "node_type": "delivery",
            "id": 7
        },
        {
            "x": 26,
            "y": 551,
            "node_type": "delivery",
            "id": 8
        },
        {
            "x": 277,
            "y": 833,
            "node_type": "delivery",
            "id": 9
        },
        {
            "x": 816,
            "y": 537,
            "node_type": "delivery",
            "id": 10
        },
        {
            "x": 789,
            "y": 150,
            "node_type": "delivery",
            "id": 11
        },
        {
            "x": 409,
            "y": 421,
            "node_type": "delivery",
            "id": 12
        },
        {
            "x": 251,
            "y": 323,
            "node_type": "delivery",
            "id": 13
        },
        {
            "x": 763,
            "y": 734,
            "node_type": "delivery",
            "id": 14
        },
        {
            "x": 925,
            "y": 790,
            "node_type": "delivery",
            "id": 15
        }
    ],
    "travel_costs": [
        [
            0,
            918.7257479792324,
            53.150729063673246,
            727.6517023961396,
            363.66605560596383,
            341.01319622560067,
            774.7031689621515,
            151.21177202850313,
            680.0838183635897,
            700.8059645864896,
            1014.015778969933,
            69.12307863514182,
            799.4979674770913,
            511.44989979469153,
            1045.8169055814694,
            637.8103166302659,
            972.8478812229588,
            124.53513560437473,
            1148.7144989073656,
            42.57933771208753,
            597.0008375203506,
            709.8091292734971,
            866.0577347960124,
            362.17399133565624,
            114.96521212958292,
            729.7081608424015,
            956.7026706349262,
            517.8967078481962,
            564.4156269984027,
            608.2795410006817,
            757.6067581535953,
            805.1049621012157
        ],
        [
            918.7257479792324,
            0,
            876.5386471799176,
            859.2985511450605,
            621.400032185387,
            605.3701347109882,
            894.0123041658878,
            1057.117779625336,
            964.8818580530985,
            550.1290757631339,
            362.8456972323084,
            850.7978608341701,
            250.42763425788297,
            895.1983020537964,
            368.2010320463537,
            519.6046574079182,
            417.50209580312287,
            906.0971250368251,
            377.04111181673545,
            930.6825452322613,
            486.56448699016244,
            994.2444367458136,
            392.149206297807,
            730.6223374630699,
            834.3248767716326,
            556.5294241996554,
            256.9844353263442,
            402.05720985949256,
            410.5337988521773,
            719.0445048813043,
            831.3705551677905,
            948.9873550263986
        ],
        [
            53.150729063673246,
            876.5386471799176,
            0,
            737.0061058091718,
            311.19447295863085,
            313.6000637755037,
            785.2299026399847,
            182.28000438885226,
            699.1573499577902,
            647.6557727682199,
            986.3513572758949,
            31.76476034853718,
            767.318708230159,
            529.9094262230103,
            1017.6463039779586,
            621.3058827984812,
            948.8371830825349,
            93.74433316206373,
            1117.6618451034285,
            54.644304369257,
            576.5353415012821,
            730.080817444206,
            814.0006142503825,
            310.38202267528317,
            115.03912377969505,
            716.6344954019447,
            924.948106652476,
            477.7970280359642,
            514.7523676487559,
            608.6189283944428,
            764.0477733754611,
            818.5847543168637
        ],
        [
            727.6517023961396,
            859.2985511450605,
            737.0061058091718,
            0,
            811.2336284942828,
            532.0234957217585,
            50.59644256269407,
            854.5642164284671,
            141.50971698084905,
            1080.9125774085526,
            663.0120662552077,
            709.2284540259225,
            610.9828148156051,
            238.51624682608102,
            693.087296089028,
            346.7463049550781,
            579.2495144581478,
            829.2659404557744,
            815.5893574587643,
            769.1475801171059,
            397.6191645280695,
            155.8589105569521,
            1099.629483053269,
            917.4164812123227,
            622.0,
            307.416655371826,
            691.8012720427739,
            640.1905966194755,
            824.6235504762159,
            168.21712160181556,
            50.24937810560445,
            100.42410069301093
        ],
        [
            363.66605560596383,
            621.400032185387,
            311.19447295863085,
            811.2336284942828,
            0,
            279.3223943761044,
            861.6936810723403,
            469.50612349574305,
            827.4811176093385,
            345.7744929863971,
            821.7889023344134,
            298.55820203102775,
            586.787866268552,
            672.7035008084914,
            848.364308537317,
            561.4312068276932,
            809.5986660068061,
            303.99013141876827,
            926.1976031063782,
            356.5613551690649,
            499.01603180659436,
            862.0904824900922,
            503.14312079168883,
            129.0310040261642,
            338.3371099953418,
            665.2435644183265,
            737.0244229331888,
            275.98550686584974,
            220.03636063160104,
            648.6670948953708,
            820.0713383602673,
            908.4629876885464
        ],
        [
            341.01319622560067,
            605.3701347109882,
            313.6000637755037,
            532.0234957217585,
            279.3223943761044,
            0,
            582.5263942517969,
            491.44379129255464,
            552.8001447177813,
            579.0138167608783,
            673.4166615105391,
            282.45353600194136,
            459.81409286797634,
            406.91153829794507,
            705.0283682235772,
            319.53090617340916,
            635.4061693121968,
            380.7059232531062,
            807.9610139109436,
            366.31816771762766,
            267.6490239100453,
            587.6027569710681,
            663.1274387325561,
            388.7467041660932,
            237.9936973955403,
            421.0890642132612,
            616.4235556822922,
            212.02122535255756,
            346.5905365124674,
            371.01212918178294,
            542.2268897795461,
            629.1486310880761
        ],
        [
            774.7031689621515,
            894.0123041658878,
            785.2299026399847,
            50.59644256269407,
            861.6936810723403,
            582.5263942517969,
            0,
            899.4442728707545,
            152.50245899656832,
            1129.242223794346,
            680.9882524684256,
            757.7631556099834,
            644.375666827977,
            277.694076278195,
            709.9647878592289,
            387.4132160884551,
            595.8070157358002,
            877.7801547084555,
            831.17386869415,
            816.4141106080908,
            441.0045351240733,
            155.65346125287417,
            1143.9165179330175,
            968.0108470466639,
            670.1910175464902,
            338.38587440967444,
            716.6344954019447,
            687.4794542384521,
            872.4058688477514,
            216.98156603730186,
            62.96824596572466,
            55.47071299343465
        ],
        [
            151.21177202850313,
            1057.117779625336,
            182.28000438885226,
            854.5642164284671,
            469.50612349574305,
            491.44379129255464,
            899.4442728707545,
            0,
            791.1238841041269,
            782.6544575992652,
            1164.7853879577988,
            211.15160430363773,
            948.4408257767061,
            626.7647086427249,
            1196.4656284239845,
            787.9524097304354,
            1124.0578276939314,
            167.50522379914005,
            1298.3258450789617,
            127.6401190848708,
            748.0541424255332,
            818.0391188690184,
            968.8162880546548,
            429.12119500206467,
            264.0378760708395,
            878.3194179795867,
            1105.9226916923262,
            659.7484369060679,
            684.0847900662607,
            747.3024822653808,
            888.3383364461988,
            924.8226857079146
        ],
        [
            680.0838183635897,
            964.8818580530985,
            699.1573499577902,
            141.50971698084905,
            827.4811176093385,
            552.8001447177813,
            152.50245899656832,
            791.1238841041269,
            0,
            1125.678906260573,
            796.3880963449918,
            674.8807302034932,
            722.0560920039385,
            169.24833824885846,
            827.3264168392062,
            445.27744160242383,
            714.2443559454985,
            792.9016332433678,
            950.5435287244871,
            722.6264595211,
            484.3222068003903,
            34.828149534536,
            1170.3956595955062,
            920.3694910197753,
            586.0588707629977,
            429.19459456055597,
            817.1327921458054,
            699.0400560769032,
            876.6829529539172,
            246.14223530308652,
            191.19100397246729,
            147.64823060233402
        ],
        [
            700.8059645864896,
            550.1290757631339,
            647.6557727682199,
            1080.9125774085526,
            345.7744929863971,
            579.0138167608783,
            1129.242223794346,
            782.6544575992652,
            1125.678906260573,
            0,
            870.4188646852733,
            639.6475592074123,
            657.3218389799628,
            985.8367004732579,
            886.8336935412411,
            768.3130872242123,
            892.8213707119695,
            616.644143732834,
            922.5323842554255,
            686.2361109705608,
            704.9120512517854,
            1160.4309544302928,
            227.6071176391459,
            354.0014124265608,
            684.1052550594828,
            860.9767708829315,
            765.4443154142567,
            444.5582076623938,
            258.75084540924695,
            912.6954585183383,
            1077.7982185919589,
            1181.2760050047575
        ],
        [
            1014.015778969933,
            362.8456972323084,
            986.3513572758949,
            663.0120662552077,
            821.7889023344134,
            673.4166615105391,
            680.9882524684256,
            1164.7853879577988,
            796.3880963449918,
            870.4188646852733,
            0,
            955.5364985179791,
            235.17015116719216,
            791.2098331037096,
            33.54101966249685,
            413.6786192202831,
            86.58521813797087,
            1045.3654863252375,
            155.97756248896826,
            1039.5773179518683,
            429.69058635255203,
            817.244761378132,
            748.024063784047,
            948.8529917748061,
            906.3625102573474,
            375.40644640176333,
            107.8702924812944,
            546.9890309686292,
            661.9252223627681,
            579.2408825350642,
            620.7253821135398,
            729.7355685452094
        ],
        [
            69.12307863514182,
            850.7978608341701,
            31.76476034853718,
            709.2284540259225,
            298.55820203102775,
            282.45353600194136,
            757.7631556099834,
            211.15160430363773,
            674.8807302034932,
            639.6475592074123,
            955.5364985179791,
            0,
            737.4449131969113,
            505.72027841485647,
            986.9270489757589,
            589.5421952668019,
            917.4949591142177,
            120.03749414245536,
            1087.5702276175089,
            84.1486779456457,
            544.8522735567872,
            706.2641149031996,
            799.4560650842546,
            310.792535302893,
            88.84255736976507,
            684.9525531013078,
            895.0005586590436,
            450.7737791841934,
            495.767082408665,
            578.6968118108135,
            735.4250471666028,
            792.0505034402794
        ],
        [
            799.4979674770913,
            250.42763425788297,
            767.318708230159,
            610.9828148156051,
            586.787866268552,
            459.81409286797634,
            644.375666827977,
            948.4408257767061,
            722.0560920039385,
            657.3218389799628,
            235.17015116719216,
            737.4449131969113,
            0,
            669.0067264235839,
            261.70594185077266,
            279.95178156246834,
            237.17082451262846,
            819.9280456235169,
            350.75062366302353,
            821.4913267953594,
            261.6123085789352,
            750.0613308256867,
            572.0707998141488,
            713.6897084868184,
            697.4983870949094,
            306.3413129174712,
            157.69908052997644,
            312.8322234041755,
            432.18514551057854,
            478.43181332348706,
            581.588342386606,
            699.1602105383286
        ],
        [
            511.44989979469153,
            895.1983020537964,
            529.9094262230103,
            238.51624682608102,
            672.7035008084914,
            406.91153829794507,
            277.694076278195,
            626.7647086427249,
            169.24833824885846,
            985.8367004732579,
            791.2098331037096,
            505.72027841485647,
            669.0067264235839,
            0,
            824.1650320172532,
            392.149206297807,
            717.2447281088931,
            623.6537500889416,
            947.0480452437457,
            553.9404300103034,
            410.2499238269278,
            200.68383093812017,
            1052.8138486931107,
            758.615185716711,
            416.9244535884169,
            417.1102971637119,
            789.2863865543355,
            579.3530875036397,
            746.0844456226118,
            213.92755783208483,
            281.4480413859723,
            298.3035366870463
        ],
        [
            1045.8169055814694,
            368.2010320463537,
            1017.6463039779586,
            693.087296089028,
            848.364308537317,
            705.0283682235772,
            709.9647878592289,
            1196.4656284239845,
            827.3264168392062,
            886.8336935412411,
            33.54101966249685,
            986.9270489757589,
            261.70594185077266,
            824.1650320172532,
            0,
            447.21918563496354,
            114.15778554264269,
            1075.7248718887186,
            123.62847568420474,
            1071.0116712716067,
            462.91359884972053,
            847.7228320624614,
            757.2218961440564,
            974.8728122170604,
            938.5829744886703,
            407.9767150218257,
            121.41251994749142,
            574.4231889469645,
            683.9371316137178,
            611.9191123016178,
            650.173053886425,
            758.0560665280636
        ],
        [
            637.8103166302659,
            519.6046574079182,
            621.3058827984812,
            346.7463049550781,
            561.4312068276932,
            319.53090617340916,
            387.4132160884551,
            787.9524097304354,
            445.27744160242383,
            768.3130872242123,
            413.6786192202831,
            589.5421952668019,
            279.95178156246834,
            392.149206297807,
            447.21918563496354,
            0,
            352.11503802024697,
            696.8536431705011,
            566.6153898368804,
            670.1619207325942,
            64.5600495662759,
            474.8526087113769,
            759.6222745549264,
            686.0728824257668,
            523.9169781558907,
            104.07689465006149,
            398.5097238462319,
            325.8972230627319,
            509.9460755805461,
            199.6246477767713,
            327.67361810191557,
            442.8001806684365
        ],
        [
            972.8478812229588,
            417.50209580312287,
            948.8371830825349,
            579.2495144581478,
            809.5986660068061,
            635.4061693121968,
            595.8070157358002,
            1124.0578276939314,
            714.2443559454985,
            892.8213707119695,
            86.58521813797087,
            917.4949591142177,
            237.17082451262846,
            717.2447281088931,
            114.15778554264269,
            352.11503802024697,
            0,
            1013.4495547386657,
            236.41488954801474,
            1000.9325651611102,
            378.30807551518114,
            734.145762093605,
            789.7170379319418,
            938.2478350627835,
            862.3004116895689,
            300.1482966801577,
            164.14932226482082,
            533.7958411228024,
            668.5701159938275,
            503.79460100322626,
            536.075554376433,
            643.9914595706996
        ],
        [
            124.53513560437473,
            906.0971250368251,
            93.74433316206373,
            829.2659404557744,
            303.99013141876827,
            380.7059232531062,
            877.7801547084555,
            167.50522379914005,
            792.9016332433678,
            616.644143732834,
            1045.3654863252375,
            120.03749414245536,
            819.9280456235169,
            623.6537500889416,
            1075.7248718887186,
            696.8536431705011,
            1013.4495547386657,
            0,
            1170.4853694087767,
            87.69264507357502,
            648.0131171511886,
            823.8021607157874,
            801.4143747151033,
            264.6828290615014,
            208.06249061279644,
            795.0729526276189,
            977.3458957810177,
            517.4958937035153,
            521.4230528083697,
            697.3757953929861,
            855.2829941019521,
            911.7856107660397
        ],
        [
            1148.7144989073656,
            377.04111181673545,
            1117.6618451034285,
            815.5893574587643,
            926.1976031063782,
            807.9610139109436,
            831.17386869415,
            1298.3258450789617,
            950.5435287244871,
            922.5323842554255,
            155.97756248896826,
            1087.5702276175089,
            350.75062366302353,
            947.0480452437457,
            123.62847568420474,
            566.6153898368804,
            236.41488954801474,
            1170.4853694087767,
            0,
            1171.686818224051,
            577.4296493946255,
            970.5596323771146,
            767.0026075574973,
            1049.4307980996173,
            1044.3342376844687,
            531.3727505245259,
            193.1450232338385,
            658.6729082025463,
            744.3560975769594,
            735.2176548478689,
            772.016191540048,
            878.3125867252502
        ],
        [
            42.57933771208753,
            930.6825452322613,
            54.644304369257,
            769.1475801171059,
            356.5613551690649,
            366.31816771762766,
            816.4141106080908,
            127.6401190848708,
            722.6264595211,
            686.2361109705608,
            1039.5773179518683,
            84.1486779456457,
            821.4913267953594,
            553.9404300103034,
            1071.0116712716067,
            670.1619207325942,
            1000.9325651611102,
            87.69264507357502,
            1171.686818224051,
            0,
            627.108443572561,
            752.3828812512949,
            859.5958352621307,
            340.58919536591293,
            151.92103211866356,
            763.8514253439604,
            979.075584416239,
            532.3532661682466,
            564.8929102051113,
            647.5376436933994,
            798.5367868796027,
            847.2360946040956
        ],
        [
            597.0008375203506,
            486.56448699016244,
            576.5353415012821,
            397.6191645280695,
            499.01603180659436,
            267.6490239100453,
            441.0045351240733,
            748.0541424255332,
            484.3222068003903,
            704.9120512517854,
            429.69058635255203,
            544.8522735567872,
            261.6123085789352,
            410.2499238269278,
            462.91359884972053,
            64.5600495662759,
            378.30807551518114,
            648.0131171511886,
            577.4296493946255,
            627.108443572561,
            0,
            515.6752854267887,
            703.0064011088376,
            624.6278892268581,
            485.00412369380945,
            166.5893153836704,
            398.05778474990285,
            261.69638897011936,
            446.3193923638093,
            239.35329536064464,
            383.2936211313724,
            495.9516105428029
        ],
        [
            709.8091292734971,
            994.2444367458136,
            730.080817444206,
            155.8589105569521,
            862.0904824900922,
            587.6027569710681,
            155.65346125287417,
            818.0391188690184,
            34.828149534536,
            1160.4309544302928,
            817.244761378132,
            706.2641149031996,
            750.0613308256867,
            200.68383093812017,
            847.7228320624614,
            474.8526087113769,
            734.145762093605,
            823.8021607157874,
            970.5596323771146,
            752.3828812512949,
            515.6752854267887,
            0,
            1204.0701806788506,
            954.409241363473,
            617.5111335028705,
            453.8512972329152,
            841.4065604688378,
            733.1520988171554,
            911.1926250799004,
            276.68212808202844,
            203.24615617521528,
            138.10503249338888
        ],
        [
            866.0577347960124,
            392.149206297807,
            814.0006142503825,
            1099.629483053269,
            503.14312079168883,
            663.1274387325561,
            1143.9165179330175,
            968.8162880546548,
            1170.3956595955062,
            227.6071176391459,
            748.024063784047,
            799.4560650842546,
            572.0707998141488,
            1052.8138486931107,
            757.2218961440564,
            759.6222745549264,
            789.7170379319418,
            801.4143747151033,
            767.0026075574973,
            859.5958352621307,
            703.0064011088376,
            1204.0701806788506,
            0,
            552.2626186878848,
            824.9151471515115,
            835.374167663808,
            640.1812243419828,
            473.85757353871634,
            319.363429340305,
            935.6943945541193,
            1086.1491610271585,
            1198.6934553921615
        ],
        [
            362.17399133565624,
            730.6223374630699,
            310.38202267528317,
            917.4164812123227,
            129.0310040261642,
            388.7467041660932,
            968.0108470466639,
            429.12119500206467,
            920.3694910197753,
            354.0014124265608,
            948.8529917748061,
            310.792535302893,
            713.6897084868184,
            758.615185716711,
            974.8728122170604,
            686.0728824257668,
            938.2478350627835,
            264.6828290615014,
            1049.4307980996173,
            340.58919536591293,
            624.6278892268581,
            954.409241363473,
            552.2626186878848,
            0,
            377.5248336202534,
            790.1240408948458,
            861.9570754973822,
            404.46137021970344,
            320.3263960400391,
            759.3800102715372,
            930.226854052279,
            1012.2450296247446
        ],
        [
            114.96521212958292,
            834.3248767716326,
            115.03912377969505,
            622.0,
            338.3371099953418,
            237.9936973955403,
            670.1910175464902,
            264.0378760708395,
            586.0588707629977,
            684.1052550594828,
            906.3625102573474,
            88.84255736976507,
            697.4983870949094,
            416.9244535884169,
            938.5829744886703,
            523.9169781558907,
            862.3004116895689,
            208.06249061279644,
            1044.3342376844687,
            151.92103211866356,
            485.00412369380945,
            617.5111335028705,
            824.9151471515115,
            377.5248336202534,
            0,
            614.9284511225676,
            853.6000234301778,
            432.62917146211953,
            510.6623150380299,
            495.98084640437474,
            649.4251304038056,
            703.7364563528026
        ],
        [
            729.7081608424015,
            556.5294241996554,
            716.6344954019447,
            307.416655371826,
            665.2435644183265,
            421.0890642132612,
            338.38587440967444,
            878.3194179795867,
            429.19459456055597,
            860.9767708829315,
            375.40644640176333,
            684.9525531013078,
            306.3413129174712,
            417.1102971637119,
            407.9767150218257,
            104.07689465006149,
            300.1482966801577,
            795.0729526276189,
            531.3727505245259,
            763.8514253439604,
            166.5893153836704,
            453.8512972329152,
            835.374167663808,
            790.1240408948458,
            614.9284511225676,
            0,
            387.9407171205415,
            423.2079866921228,
            604.1696781534141,
            204.00490190189058,
            275.48139683107456,
            392.9478336878828
        ],
        [
            956.7026706349262,
            256.9844353263442,
            924.948106652476,
            691.8012720427739,
            737.0244229331888,
            616.4235556822922,
            716.6344954019447,
            1105.9226916923262,
            817.1327921458054,
            765.4443154142567,
            107.8702924812944,
            895.0005586590436,
            157.69908052997644,
            789.2863865543355,
            121.41251994749142,
            398.5097238462319,
            164.14932226482082,
            977.3458957810177,
            193.1450232338385,
            979.075584416239,
            398.05778474990285,
            841.4065604688378,
            640.1812243419828,
            861.9570754973822,
            853.6000234301778,
            387.9407171205415,
            0,
            466.73439984642226,
            565.1309582742747,
            584.5784806165892,
            654.2904553789548,
            768.600026021337
        ],
        [
            517.8967078481962,
            402.05720985949256,
            477.7970280359642,
            640.1905966194755,
            275.98550686584974,
            212.02122535255756,
            687.4794542384521,
            659.7484369060679,
            699.0400560769032,
            444.5582076623938,
            546.9890309686292,
            450.7737791841934,
            312.8322234041755,
            579.3530875036397,
            574.4231889469645,
            325.8972230627319,
            533.7958411228024,
            517.4958937035153,
            658.6729082025463,
            532.3532661682466,
            261.69638897011936,
            733.1520988171554,
            473.85757353871634,
            404.46137021970344,
            432.62917146211953,
            423.2079866921228,
            466.73439984642226,
            0,
            185.92471594707357,
            472.53042230104086,
            634.3634604861791,
            740.5653246000652
        ],
        [
            564.4156269984027,
            410.5337988521773,
            514.7523676487559,
            824.6235504762159,
            220.03636063160104,
            346.5905365124674,
            872.4058688477514,
            684.0847900662607,
            876.6829529539172,
            258.75084540924695,
            661.9252223627681,
            495.767082408665,
            432.18514551057854,
            746.0844456226118,
            683.9371316137178,
            509.9460755805461,
            668.5701159938275,
            521.4230528083697,
            744.3560975769594,
            564.8929102051113,
            446.3193923638093,
            911.1926250799004,
            319.363429340305,
            320.3263960400391,
            510.6623150380299,
            604.1696781534141,
            565.1309582742747,
            185.92471594707357,
            0,
            656.5554051258736,
            819.9786582588598,
            925.0475663445637
        ],
        [
            608.2795410006817,
            719.0445048813043,
            608.6189283944428,
            168.21712160181556,
            648.6670948953708,
            371.01212918178294,
            216.98156603730186,
            747.3024822653808,
            246.14223530308652,
            912.6954585183383,
            579.2408825350642,
            578.6968118108135,
            478.43181332348706,
            213.92755783208483,
            611.9191123016178,
            199.6246477767713,
            503.79460100322626,
            697.3757953929861,
            735.2176548478689,
            647.5376436933994,
            239.35329536064464,
            276.68212808202844,
            935.6943945541193,
            759.3800102715372,
            495.98084640437474,
            204.00490190189058,
            584.5784806165892,
            472.53042230104086,
            656.5554051258736,
            0,
            171.40595088852663,
            268.6000744601535
        ],
        [
            757.6067581535953,
            831.3705551677905,
            764.0477733754611,
            50.24937810560445,
            820.0713383602673,
            542.2268897795461,
            62.96824596572466,
            888.3383364461988,
            191.19100397246729,
            1077.7982185919589,
            620.7253821135398,
            735.4250471666028,
            581.588342386606,
            281.4480413859723,
            650.173053886425,
            327.67361810191557,
            536.075554376433,
            855.2829941019521,
            772.016191540048,
            798.5367868796027,
            383.2936211313724,
            203.24615617521528,
            1086.1491610271585,
            930.226854052279,
            649.4251304038056,
            275.48139683107456,
            654.2904553789548,
            634.3634604861791,
            819.9786582588598,
            171.40595088852663,
            0,
            117.61802582937703
        ],
        [
            805.1049621012157,
            948.9873550263986,
            818.5847543168637,
            100.42410069301093,
            908.4629876885464,
            629.1486310880761,
            55.47071299343465,
            924.8226857079146,
            147.64823060233402,
            1181.2760050047575,
            729.7355685452094,
            792.0505034402794,
            699.1602105383286,
            298.3035366870463,
            758.0560665280636,
            442.8001806684365,
            643.9914595706996,
            911.7856107660397,
            878.3125867252502,
            847.2360946040956,
            495.9516105428029,
            138.10503249338888,
            1198.6934553921615,
            1012.2450296247446,
            703.7364563528026,
            392.9478336878828,
            768.600026021337,
            740.5653246000652,
            925.0475663445637,
            268.6000744601535,
            117.61802582937703,
            0
        ]
    ],
    "incompatibilities": [
        [
            0,
            0,
            1,
            0,
            1,
            0,
            0,
            1,
            1,
            1,
            0,
            1,
            1,
            1,
            0
        ],
        [
            0,
            0,
            1,
            1,
            1,
            1,
            1,
            0,
            1,
            1,
            1,
            1,
            1,
            1,
            1
        ],
        [
            1,
            1,
            0,
            0,
            1,
            1,
            1,
            1,
            1,
            1,
            1,
            1,
            1,
            0,
            1
        ],
        [
            0,
            1,
            0,
            0,
            1,
            1,
            0,
            1,
            1,
            1,
            0,
            1,
            0,
            1,
            1
        ],
        [
            1,
            1,
            1,
            1,
            0,
            1,
            0,
            0,
            0,
            1,
            0,
            1,
            1,
            1,
            0
        ],
        [
            0,
            1,
            1,
            1,
            1,
            0,
            1,
            1,
            0,
            1,
            1,
            1,
            0,
            1,
            1
        ],
        [
            0,
            1,
            1,
            0,
            0,
            1,
            0,
            1,
            1,
            1,
            1,
            1,
            1,
            1,
            1
        ],
        [
            1,
            0,
            1,
            1,
            0,
            1,
            1,
            0,
            1,
            1,
            1,
            1,
            0,
            1,
            1
        ],
        [
            1,
            1,
            1,
            1,
            0,
            0,
            1,
            1,
            0,
            1,
            1,
            1,
            1,
            0,
            0
        ],
        [
            1,
            1,
            1,
            1,
            1,
            1,
            1,
            1,
            1,
            0,
            1,
            1,
            1,
            0,
            0
        ],
        [
            0,
            1,
            1,
            0,
            0,
            1,
            1,
            1,
            1,
            1,
            0,
            1,
            1,
            0,
            1
        ],
        [
            1,
            1,
            1,
            1,
            1,
            1,
            1,
            1,
            1,
            1,
            1,
            0,
            1,
            1,
            1
        ],
        [
            1,
            1,
            1,
            0,
            1,
            0,
            1,
            0,
            1,
            1,
            1,
            1,
            0,
            0,
            1
        ],
        [
            1,
            1,
            0,
            1,
            1,
            1,
            1,
            1,
            0,
            0,
            0,
            1,
            0,
            0,
            1
        ],
        [
            0,
            1,
            1,
            1,
            0,
            1,
            1,
            1,
            0,
            0,
            1,
            1,
            1,
            1,
            0
        ]
    ]
}